hgeom/.gitignore
hgeom/__init__.py
hgeom/_bcc.cpython-39-i386-linux-gnu.so
hgeom/_bvh.cpython-39-i386-linux-gnu.so
hgeom/_cookie_cutter.cpython-39-i386-linux-gnu.so
hgeom/_expand_xforms.cpython-39-i386-linux-gnu.so
hgeom/_phmap.cpython-39-i386-linux-gnu.so
hgeom/_qcp.cpython-39-i386-linux-gnu.so
hgeom/_xbin.cpython-39-i386-linux-gnu.so
hgeom/_xbin_util.cpython-39-i386-linux-gnu.so
hgeom/_xform_dist.cpython-39-i386-linux-gnu.so
hgeom/timer.py
hgeom/bvh/bvh.cpp
hgeom/bvh/bvh.hpp
hgeom/bvh/bvh_algo.hpp
hgeom/bvh/bvh_nd.cpp
hgeom/bvh/bvh_test.cpp
hgeom/cluster/cookie_cutter.cpp
hgeom/extern/Eigen/Cholesky
hgeom/extern/Eigen/CholmodSupport
hgeom/extern/Eigen/Core
hgeom/extern/Eigen/Dense
hgeom/extern/Eigen/Eigen
hgeom/extern/Eigen/Eigenvalues
hgeom/extern/Eigen/Geometry
hgeom/extern/Eigen/Householder
hgeom/extern/Eigen/IterativeLinearSolvers
hgeom/extern/Eigen/Jacobi
hgeom/extern/Eigen/KLUSupport
hgeom/extern/Eigen/LU
hgeom/extern/Eigen/MetisSupport
hgeom/extern/Eigen/OrderingMethods
hgeom/extern/Eigen/PaStiXSupport
hgeom/extern/Eigen/PardisoSupport
hgeom/extern/Eigen/QR
hgeom/extern/Eigen/QtAlignedMalloc
hgeom/extern/Eigen/SPQRSupport
hgeom/extern/Eigen/SVD
hgeom/extern/Eigen/Sparse
hgeom/extern/Eigen/SparseCholesky
hgeom/extern/Eigen/SparseCore
hgeom/extern/Eigen/SparseLU
hgeom/extern/Eigen/SparseQR
hgeom/extern/Eigen/StdDeque
hgeom/extern/Eigen/StdList
hgeom/extern/Eigen/StdVector
hgeom/extern/Eigen/SuperLUSupport
hgeom/extern/Eigen/UmfPackSupport
hgeom/extern/Eigen/src/Cholesky/LDLT.h
hgeom/extern/Eigen/src/Cholesky/LLT.h
hgeom/extern/Eigen/src/Cholesky/LLT_LAPACKE.h
hgeom/extern/Eigen/src/CholmodSupport/CholmodSupport.h
hgeom/extern/Eigen/src/Core/ArithmeticSequence.h
hgeom/extern/Eigen/src/Core/Array.h
hgeom/extern/Eigen/src/Core/ArrayBase.h
hgeom/extern/Eigen/src/Core/ArrayWrapper.h
hgeom/extern/Eigen/src/Core/Assign.h
hgeom/extern/Eigen/src/Core/AssignEvaluator.h
hgeom/extern/Eigen/src/Core/Assign_MKL.h
hgeom-2.0.5.dist-info/METADATA
hgeom-2.0.5.dist-info/WHEEL
hgeom-2.0.5.dist-info/RECORD
hgeom-2.0.5.dist-info/licenses/LICENSE
